pybag/__init__.py
pybag/crashdbg.py
pybag/kerneldbg.py
pybag/pydbg.py
pybag/userdbg.py
pybag/dbgeng/__init__.py
pybag/dbgeng/breakpoints.py
pybag/dbgeng/callbacks.py
pybag/dbgeng/core.py
pybag/dbgeng/dbgengstructs.py
pybag/dbgeng/exception.py
pybag/dbgeng/idebugadvanced.py
pybag/dbgeng/idebugbreakpoint.py
pybag/dbgeng/idebugclient.py
pybag/dbgeng/idebugcontrol.py
pybag/dbgeng/idebugdataspaces.py
pybag/dbgeng/idebugregisters.py
pybag/dbgeng/idebugsymbols.py
pybag/dbgeng/idebugsystemobjects.py
pybag/dbgeng/modules.py
pybag/dbgeng/pefile2.py
pybag/dbgeng/registers.py
pybag/dbgeng/util.py
pybag/dbgeng/tlb/dbgeng.tlb
pybag-2.2.16.dist-info/licenses/LICENSE
pybag-2.2.16.dist-info/METADATA
pybag-2.2.16.dist-info/WHEEL
pybag-2.2.16.dist-info/top_level.txt
pybag-2.2.16.dist-info/RECORD
