Metadata-Version: 2.4
Name: Pybag
Version: 2.2.16
Summary: Python wrappers for DbgEng from Windbg
Home-page: https://github.com/dshikashio/Pybag
Author: Doug S
License: MIT
Keywords: windows,debugging,dbgeng,windbg,reverseengineering
Classifier: License :: OSI Approved :: MIT License
Classifier: Programming Language :: Python :: 3
Classifier: Development Status :: 5 - Production/Stable
Classifier: Intended Audience :: Developers
Classifier: Intended Audience :: Science/Research
Classifier: Natural Language :: English
Classifier: Operating System :: Microsoft :: Windows
Classifier: Programming Language :: Python
Classifier: Topic :: Software Development :: Libraries :: Python Modules
Requires-Python: >=3.7.0
License-File: LICENSE
Requires-Dist: capstone>=4.0.2
Requires-Dist: comtypes>=1.1.14
Requires-Dist: pywin32>=301
Requires-Dist: win32more>=0.5.8
Dynamic: author
Dynamic: classifier
Dynamic: description
Dynamic: description-content-type
Dynamic: home-page
Dynamic: keywords
Dynamic: license
Dynamic: license-file
Dynamic: requires-dist
Dynamic: requires-python
Dynamic: summary
